library_test/__init__.py
library_test/circle.py
library_test/rectangle.py
testjuanmferreira93-0.0.10.dist-info/METADATA
testjuanmferreira93-0.0.10.dist-info/WHEEL
testjuanmferreira93-0.0.10.dist-info/top_level.txt
testjuanmferreira93-0.0.10.dist-info/RECORD
