Metadata-Version: 2.1
Name: testjuanmferreira93
Version: 0.0.10
Summary: This is a test library
Author: Juanma Ferreira
